LICENSE
MANIFEST.in
README.rst
setup.py
tox.ini
tinytask/__init__.py
tinytask/exceptions.py
tinytask/scheduler.py
tinytask.egg-info/PKG-INFO
tinytask.egg-info/SOURCES.txt
tinytask.egg-info/dependency_links.txt
tinytask.egg-info/entry_points.txt
tinytask.egg-info/top_level.txt